<?xml version="1.0" encoding="utf-8" ?>
<dwsync>
<file name="antarctica" server="www.yoktemplates.com//Previews/neu/" local="130301251480000000" remote="130349206200000000" Dst="1" />
<file name="africa" server="www.yoktemplates.com//Previews/neu/" local="130301251480000000" remote="130349206200000000" Dst="1" />
<file name="asia" server="www.yoktemplates.com//Previews/neu/" local="130301251480000000" remote="130349206200000000" Dst="1" />
<file name="backward" server="www.yoktemplates.com//Previews/neu/" local="130301251480000000" remote="130349206200000000" Dst="1" />
<file name="etcetera" server="www.yoktemplates.com//Previews/neu/" local="130301251480000000" remote="130349206200000000" Dst="1" />
<file name="factory" server="www.yoktemplates.com//Previews/neu/" local="130301251480000000" remote="130349206200000000" Dst="1" />
<file name="iso3166.tab" server="www.yoktemplates.com//Previews/neu/" local="130301251480000000" remote="130349206200000000" Dst="1" />
<file name="europe" server="www.yoktemplates.com//Previews/neu/" local="130301251480000000" remote="130349206200000000" Dst="1" />
<file name="australasia" server="www.yoktemplates.com//Previews/neu/" local="130301251480000000" remote="130349206200000000" Dst="1" />
<file name="leapseconds" server="www.yoktemplates.com//Previews/neu/" local="130301251480000000" remote="130349206200000000" Dst="1" />
<file name="pacificnew" server="www.yoktemplates.com//Previews/neu/" local="130301251480000000" remote="130349206200000000" Dst="1" />
<file name="solar87" server="www.yoktemplates.com//Previews/neu/" local="130301251480000000" remote="130349206200000000" Dst="1" />
<file name="solar88" server="www.yoktemplates.com//Previews/neu/" local="130301251480000000" remote="130349206200000000" Dst="1" />
<file name="solar89" server="www.yoktemplates.com//Previews/neu/" local="130301251480000000" remote="130349206200000000" Dst="1" />
<file name="northamerica" server="www.yoktemplates.com//Previews/neu/" local="130301251480000000" remote="130349206200000000" Dst="1" />
<file name="systemv" server="www.yoktemplates.com//Previews/neu/" local="130301251480000000" remote="130349206200000000" Dst="1" />
<file name="yearistype.sh" server="www.yoktemplates.com//Previews/neu/" local="130301251480000000" remote="130349206200000000" Dst="1" />
<file name="southamerica" server="www.yoktemplates.com//Previews/neu/" local="130301251480000000" remote="130349206200000000" Dst="1" />
<file name="zone.tab" server="www.yoktemplates.com//Previews/neu/" local="130301251480000000" remote="130349206200000000" Dst="1" />
</dwsync>